pyscrap/__init__.py
pyscrap/app/__init__.py
pyscrap/app/main.py
pyscrap/scraped_data/__init__.py
pyscrap_tool-0.1.dist-info/LICENSE.md
pyscrap_tool-0.1.dist-info/METADATA
pyscrap_tool-0.1.dist-info/WHEEL
pyscrap_tool-0.1.dist-info/entry_points.txt
pyscrap_tool-0.1.dist-info/top_level.txt
pyscrap_tool-0.1.dist-info/RECORD
