Metadata-Version: 2.1
Name: pyscrap-tool
Version: 0.1
Summary: A CLI tool for web scraping
Home-page: https://github.com/h471x/web_scraper
Author: Hatix Ntsoa
Author-email: hatixntsoa@gmail.com
License: MIT
Classifier: Programming Language :: Python :: 3
Classifier: License :: OSI Approved :: MIT License
Classifier: Operating System :: OS Independent
License-File: LICENSE.md
